Metadata-Version: 2.1
Name: hypermea
Version: 0.9.51
Summary: Simple Commands, Serious APIs.
Home-page: https://github.com/pointw-dev/hypermea
Author: Michael Ottoson
Author-email: michael@pointw.com
License: MIT
Project-URL: Documentation, https://pointw-dev.github.io/hypermea
Classifier: Development Status :: 4 - Beta
Classifier: License :: OSI Approved :: MIT License
Classifier: Programming Language :: Python :: 3
Classifier: Operating System :: OS Independent
Classifier: Framework :: Flask
Classifier: Intended Audience :: Developers
Classifier: Topic :: Internet :: WWW/HTTP :: HTTP Servers
Classifier: Topic :: Software Development :: Code Generators
Classifier: Topic :: Utilities
Requires-Dist: libcst
Requires-Dist: inflect ==4.1.0
Requires-Dist: click
Requires-Dist: requests
Requires-Dist: hypermea-core ==0.9.51
